align_browser/__init__.py
align_browser/build.py
align_browser/conftest.py
align_browser/csv_exporter.py
align_browser/experiment_models.py
align_browser/experiment_parser.py
align_browser/test_basic_load.py
align_browser/test_build.py
align_browser/test_config.py
align_browser/test_double_render.py
align_browser/test_experiment_parser.py
align_browser/test_frontend.py
align_browser/test_frontend_real_data.py
align_browser/test_kdma_parsing.py
align_browser/test_link_cascade.py
align_browser/test_parsing.py
align_browser/test_spinner.py
align_browser/static/__init__.py
align_browser/static/app.js
align_browser/static/index.html
align_browser/static/notifications.js
align_browser/static/state.js
align_browser/static/style.css
align_browser/static/table-formatter.js
align_browser-0.8.0.dist-info/METADATA
align_browser-0.8.0.dist-info/WHEEL
align_browser-0.8.0.dist-info/entry_points.txt
align_browser-0.8.0.dist-info/top_level.txt
align_browser-0.8.0.dist-info/RECORD
