Metadata-Version: 2.4
Name: align-browser
Version: 0.8.0
Summary: Static web application for visualizing ADM results
Requires-Python: >=3.10
Requires-Dist: pyyaml
Requires-Dist: pydantic
Requires-Dist: waitress
